mochad_dispatch/__init__.py
mochad_dispatch/main.py
mochad_dispatch-1.0.0.dist-info/LICENSE
mochad_dispatch-1.0.0.dist-info/METADATA
mochad_dispatch-1.0.0.dist-info/WHEEL
mochad_dispatch-1.0.0.dist-info/entry_points.txt
mochad_dispatch-1.0.0.dist-info/top_level.txt
mochad_dispatch-1.0.0.dist-info/RECORD
