Metadata-Version: 2.2
Name: mochad_dispatch
Version: 1.0.0
Summary: mochad_dispatch is a daemon written in Python that translates mochad's tcp-based events to MQTT messages
Home-page: https://github.com/StoaferP/mochad_dispatch
Download-URL: https://github.com/StoaferP/mochad_dispatch/archive/1.0.0.zip
Author: Chris Przybycien
Author-email: chrisisdiy@gmail.com
License: MIT
Classifier: License :: OSI Approved :: MIT License
Classifier: Operating System :: POSIX :: Linux
Classifier: Programming Language :: Python :: 3.4
License-File: LICENSE
Requires-Dist: paho-mqtt
Requires-Dist: pytz
Dynamic: author
Dynamic: author-email
Dynamic: classifier
Dynamic: description
Dynamic: download-url
Dynamic: home-page
Dynamic: license
Dynamic: requires-dist
Dynamic: summary
